pipelines/hello_world.py
pipelines/test.py
pipelines_test-1.0.4.dist-info/METADATA
pipelines_test-1.0.4.dist-info/WHEEL
pipelines_test-1.0.4.dist-info/top_level.txt
pipelines_test-1.0.4.dist-info/RECORD
