Metadata-Version: 2.1
Name: pipelines-test
Version: 1.0.4
Summary: SkillCorner API client
Author: SkillCorner
Author-email: support@skillcorner.com
Requires-Python: >=3.6
Requires-Dist: requests (>=2.20.0)
Requires-Dist: makefun (>=1.10.0)
Provides-Extra: release
Requires-Dist: Sphinx (==4.2.0) ; extra == 'release'
Requires-Dist: sphinx-rtd-theme (==1.0.0) ; extra == 'release'
Provides-Extra: test
Requires-Dist: mock (==4.0.3) ; extra == 'test'
